localsockets/__init__.py
localsockets-0.0.0.data/scripts/localsockets
localsockets-0.0.0.dist-info/METADATA
localsockets-0.0.0.dist-info/WHEEL
localsockets-0.0.0.dist-info/top_level.txt
localsockets-0.0.0.dist-info/RECORD
