Metadata-Version: 2.1
Name: localsockets
Version: 0.0.0
Summary: A python package to help transfer data between programs. 
Home-page: https://pypi.org/project/localsockets
Author: Sandra Mattar
Author-email: sandrawmattar1@gmail.com
License: UNKNOWN
Platform: UNKNOWN
Requires-Dist: watchdog
